peskytm/__init__.py
peskytm/_version.py
peskytm/peskytm.py
peskytm/resources/__init__.py
peskytm/resources/loggingConfiguration.json
peskytm-1.0.0.dist-info/licenses/LICENSE
peskytm-1.0.0.dist-info/METADATA
peskytm-1.0.0.dist-info/WHEEL
peskytm-1.0.0.dist-info/entry_points.txt
peskytm-1.0.0.dist-info/top_level.txt
peskytm-1.0.0.dist-info/RECORD
