Metadata-Version: 2.4
Name: peskytm
Version: 1.0.0
Summary: Unmount pesky Time Machine Volumes
Author-email: "Humberto A. Sanchez II" <Humberto.A.Sanchez.II@gmail.com>
Maintainer-email: "Humberto A. Sanchez II" <Humberto.A.Sanchez.II@gmail.com>
License-Expression: AGPL-1.0-or-later
Project-URL: Repository, https://github.com/hasii2011/peskytm
Keywords: OSX,time machine
License-File: LICENSE
Requires-Dist: click>=8.2.1
Provides-Extra: test
Requires-Dist: mypy==1.16.1; extra == "test"
Requires-Dist: mypy-extensions==1.1.0; extra == "test"
Requires-Dist: types-Deprecated==1.2.9.20240311; extra == "test"
Requires-Dist: html-testRunner~=1.2.1; extra == "test"
Provides-Extra: deploy
Requires-Dist: wheel==0.45.1; extra == "deploy"
Requires-Dist: setuptools==75.7.0; extra == "deploy"
Requires-Dist: twine==6.0.1; extra == "deploy"
Requires-Dist: build==1.2.2.post1; extra == "deploy"
Requires-Dist: pkginfo==1.12.1.2; extra == "deploy"
Requires-Dist: buildlackey>=1.8.2; extra == "deploy"
Dynamic: license-file
